pelican_decorate_content/__init__.py
pelican_decorate_content/decorate_content.py
pelican_decorate_content-0.1.1.dist-info/LICENSE
pelican_decorate_content-0.1.1.dist-info/METADATA
pelican_decorate_content-0.1.1.dist-info/WHEEL
pelican_decorate_content-0.1.1.dist-info/top_level.txt
pelican_decorate_content-0.1.1.dist-info/RECORD
