Metadata-Version: 2.1
Name: pelican-decorate-content
Version: 0.1.1
Summary: A Pelican plugin for rule-based addition of classes to your content
Home-page: https://github.com/offen/pelican-decorate-content
Author: Frederik Ring
Author-email: frederik.ring@gmail.com
License: UNKNOWN
Platform: UNKNOWN
Classifier: Programming Language :: Python :: 3
Classifier: License :: OSI Approved :: MIT License
Classifier: Operating System :: OS Independent
Requires-Dist: pelican (>=3)
Requires-Dist: beautifulsoup4
